libname/__init__.py
libname/hello.py
idkwtifa-0.0.1.dist-info/METADATA
idkwtifa-0.0.1.dist-info/WHEEL
idkwtifa-0.0.1.dist-info/top_level.txt
idkwtifa-0.0.1.dist-info/RECORD
