Metadata-Version: 2.1
Name: idkwtifa
Version: 0.0.1
Summary: I dont know what this is for actually
Author: Me (me)
Author-email: <adityasinghshishodiaproff@gmail.com>
Classifier: Development Status :: 1 - Planning
Classifier: Intended Audience :: Developers
Classifier: Programming Language :: Python :: 3
Classifier: Operating System :: Unix
Classifier: Operating System :: MacOS :: MacOS X
Classifier: Operating System :: Microsoft :: Windows
